autoclean_view/__init__.py
autoclean_view/cli.py
autoclean_view/viewer.py
autoclean_view-0.1.1.dist-info/licenses/LICENSE
autoclean_view-0.1.1.dist-info/METADATA
autoclean_view-0.1.1.dist-info/WHEEL
autoclean_view-0.1.1.dist-info/entry_points.txt
autoclean_view-0.1.1.dist-info/top_level.txt
autoclean_view-0.1.1.dist-info/RECORD
